examples/one_shot_debouncer/one-shot-debouncer-tb.v
`default_nettype none

`timescale 1us/10ns

module OneShotDebouncerTB;
  reg clk = 0;
  reg trigger = 0;
  reg [7:0] counter = 0;
  wire out;

  OneShotDebouncer osd (
    .clk(clk),
    .in(trigger),
    .o(out)
  );

  always #1 begin
    clk = ~clk;
    if (clk == 1) begin
      counter = counter + 1;
    end
  end

  initial begin
    repeat(1) @(posedge clk);
    if (~(out == 1'b0)) begin
      $display("Test failed - sending an output pulse before triggered");
      $finish();
    end
    trigger = 1'b1;
    repeat(127) @(posedge clk);
    if (~(out == 1'b0)) begin
      $display("Test failed - output went high too early!");
      $finish();
    end
    repeat(2) @(posedge clk);
    trigger = 1'b0;
    repeat(1) @(posedge clk);
    if (~(out == 1'b1)) begin
      $display("Test failed - output not high when it should be");
      $finish();
    end
    repeat(1) @(posedge clk);
    if (~(out == 1'b0)) begin
      $display("Test failed - output was high for longer than one clock cycle");
      $finish();
    end
    $display("Test passed!");
    $finish;
  end
  initial begin
    $dumpfile("one-shot-debouncer.vcd");
    $dumpvars(0);
  end
endmodule

module OneShotDebouncer(
  input clk,
  input in,
  output reg o
);
  reg [7:0] counter = 0;
  reg [2:0] state = 0;

  initial begin
    o = 0;
  end

  always @(posedge clk) begin
    case (state)
      0 : begin
        if (in == 1'b1) begin
          state <= 1;
          o <= 1'b0;
        end
      end

      1 : begin
        if (in == 1'b0) begin
          counter <= 0;
          state <= 0;
        end else begin
          if ((counter[7]) == 1'b0) begin
            counter <= counter + 1;
          end else begin
            o <= 1'b1;
            state <= 2;
          end
        end
      end

      2 : begin
        o <= 1'b0;
        state <= 3;
      end

      3 : begin
        if (in == 1'b1) begin
          counter <= 0;
        end else begin
          if ((counter[7]) == 0) begin
            counter <= counter + 1;
          end else begin
            state <= 0;
          end
        end
      end
    endcase
  end
endmodule

examples/one_shot_debouncer/one-shot-debouncer.vcd
$date
	Fri Mar 20 08:30:56 2020
$end
$version
	Icarus Verilog
$end
$timescale
	10ns
$end
$scope module OneShotDebouncerTB $end
$var wire 1 ! out $end
$var reg 1 " clk $end
$var reg 8 # counter [7:0] $end
$var reg 1 $ trigger $end
$scope module osd $end
$var wire 1 " clk $end
$var wire 1 $ in $end
$var reg 8 % counter [7:0] $end
$var reg 1 ! o $end
$var reg 3 & state [2:0] $end
$upscope $end
$upscope $end
$enddefinitions $end
#0
$dumpvars
b0 &
b0 %
0$
b0 #
0"
0!
$end
#100
b1 &
1$
b1 #
1"
#200
0"
#300
b1 %
b10 #
1"
#400
0"
#500
b10 %
b11 #
1"
#600
0"
#700
b11 %
b100 #
1"
#800
0"
#900
b100 %
b101 #
1"
#1000
0"
#1100
b101 %
b110 #
1"
#1200
0"
#1300
b110 %
b111 #
1"
#1400
0"
#1500
b111 %
b1000 #
1"
#1600
0"
#1700
b1000 %
b1001 #
1"
#1800
0"
#1900
b1001 %
b1010 #
1"
#2000
0"
#2100
b1010 %
b1011 #
1"
#2200
0"
#2300
b1011 %
b1100 #
1"
#2400
0"
#2500
b1100 %
b1101 #
1"
#2600
0"
#2700
b1101 %
b1110 #
1"
#2800
0"
#2900
b1110 %
b1111 #
1"
#3000
0"
#3100
b1111 %
b10000 #
1"
#3200
0"
#3300
b10000 %
b10001 #
1"
#3400
0"
#3500
b10001 %
b10010 #
1"
#3600
0"
#3700
b10010 %
b10011 #
1"
#3800
0"
#3900
b10011 %
b10100 #
1"
#4000
0"
#4100
b10100 %
b10101 #
1"
#4200
0"
#4300
b10101 %
b10110 #
1"
#4400
0"
#4500
b10110 %
b10111 #
1"
#4600
0"
#4700
b10111 %
b11000 #
1"
#4800
0"
#4900
b11000 %
b11001 #
1"
#5000
0"
#5100
b11001 %
b11010 #
1"
#5200
0"
#5300
b11010 %
b11011 #
1"
#5400
0"
#5500
b11011 %
b11100 #
1"
#5600
0"
#5700
b11100 %
b11101 #
1"
#5800
0"
#5900
b11101 %
b11110 #
1"
#6000
0"
#6100
b11110 %
b11111 #
1"
#6200
0"
#6300
b11111 %
b100000 #
1"
#6400
0"
#6500
b100000 %
b100001 #
1"
#6600
0"
#6700
b100001 %
b100010 #
1"
#6800
0"
#6900
b100010 %
b100011 #
1"
#7000
0"
#7100
b100011 %
b100100 #
1"
#7200
0"
#7300
b100100 %
b100101 #
1"
#7400
0"
#7500
b100101 %
b100110 #
1"
#7600
0"
#7700
b100110 %
b100111 #
1"
#7800
0"
#7900
b100111 %
b101000 #
1"
#8000
0"
#8100
b101000 %
b101001 #
1"
#8200
0"
#8300
b101001 %
b101010 #
1"
#8400
0"
#8500
b101010 %
b101011 #
1"
#8600
0"
#8700
b101011 %
b101100 #
1"
#8800
0"
#8900
b101100 %
b101101 #
1"
#9000
0"
#9100
b101101 %
b101110 #
1"
#9200
0"
#9300
b101110 %
b101111 #
1"
#9400
0"
#9500
b101111 %
b110000 #
1"
#9600
0"
#9700
b110000 %
b110001 #
1"
#9800
0"
#9900
b110001 %
b110010 #
1"
#10000
0"
#10100
b110010 %
b110011 #
1"
#10200
0"
#10300
b110011 %
b110100 #
1"
#10400
0"
#10500
b110100 %
b110101 #
1"
#10600
0"
#10700
b110101 %
b110110 #
1"
#10800
0"
#10900
b110110 %
b110111 #
1"
#11000
0"
#11100
b110111 %
b111000 #
1"
#11200
0"
#11300
b111000 %
b111001 #
1"
#11400
0"
#11500
b111001 %
b111010 #
1"
#11600
0"
#11700
b111010 %
b111011 #
1"
#11800
0"
#11900
b111011 %
b111100 #
1"
#12000
0"
#12100
b111100 %
b111101 #
1"
#12200
0"
#12300
b111101 %
b111110 #
1"
#12400
0"
#12500
b111110 %
b111111 #
1"
#12600
0"
#12700
b111111 %
b1000000 #
1"
#12800
0"
#12900
b1000000 %
b1000001 #
1"
#13000
0"
#13100
b1000001 %
b1000010 #
1"
#13200
0"
#13300
b1000010 %
b1000011 #
1"
#13400
0"
#13500
b1000011 %
b1000100 #
1"
#13600
0"
#13700
b1000100 %
b1000101 #
1"
#13800
0"
#13900
b1000101 %
b1000110 #
1"
#14000
0"
#14100
b1000110 %
b1000111 #
1"
#14200
0"
#14300
b1000111 %
b1001000 #
1"
#14400
0"
#14500
b1001000 %
b1001001 #
1"
#14600
0"
#14700
b1001001 %
b1001010 #
1"
#14800
0"
#14900
b1001010 %
b1001011 #
1"
#15000
0"
#15100
b1001011 %
b1001100 #
1"
#15200
0"
#15300
b1001100 %
b1001101 #
1"
#15400
0"
#15500
b1001101 %
b1001110 #
1"
#15600
0"
#15700
b1001110 %
b1001111 #
1"
#15800
0"
#15900
b1001111 %
b1010000 #
1"
#16000
0"
#16100
b1010000 %
b1010001 #
1"
#16200
0"
#16300
b1010001 %
b1010010 #
1"
#16400
0"
#16500
b1010010 %
b1010011 #
1"
#16600
0"
#16700
b1010011 %
b1010100 #
1"
#16800
0"
#16900
b1010100 %
b1010101 #
1"
#17000
0"
#17100
b1010101 %
b1010110 #
1"
#17200
0"
#17300
b1010110 %
b1010111 #
1"
#17400
0"
#17500
b1010111 %
b1011000 #
1"
#17600
0"
#17700
b1011000 %
b1011001 #
1"
#17800
0"
#17900
b1011001 %
b1011010 #
1"
#18000
0"
#18100
b1011010 %
b1011011 #
1"
#18200
0"
#18300
b1011011 %
b1011100 #
1"
#18400
0"
#18500
b1011100 %
b1011101 #
1"
#18600
0"
#18700
b1011101 %
b1011110 #
1"
#18800
0"
#18900
b1011110 %
b1011111 #
1"
#19000
0"
#19100
b1011111 %
b1100000 #
1"
#19200
0"
#19300
b1100000 %
b1100001 #
1"
#19400
0"
#19500
b1100001 %
b1100010 #
1"
#19600
0"
#19700
b1100010 %
b1100011 #
1"
#19800
0"
#19900
b1100011 %
b1100100 #
1"
#20000
0"
#20100
b1100100 %
b1100101 #
1"
#20200
0"
#20300
b1100101 %
b1100110 #
1"
#20400
0"
#20500
b1100110 %
b1100111 #
1"
#20600
0"
#20700
b1100111 %
b1101000 #
1"
#20800
0"
#20900
b1101000 %
b1101001 #
1"
#21000
0"
#21100
b1101001 %
b1101010 #
1"
#21200
0"
#21300
b1101010 %
b1101011 #
1"
#21400
0"
#21500
b1101011 %
b1101100 #
1"
#21600
0"
#21700
b1101100 %
b1101101 #
1"
#21800
0"
#21900
b1101101 %
b1101110 #
1"
#22000
0"
#22100
b1101110 %
b1101111 #
1"
#22200
0"
#22300
b1101111 %
b1110000 #
1"
#22400
0"
#22500
b1110000 %
b1110001 #
1"
#22600
0"
#22700
b1110001 %
b1110010 #
1"
#22800
0"
#22900
b1110010 %
b1110011 #
1"
#23000
0"
#23100
b1110011 %
b1110100 #
1"
#23200
0"
#23300
b1110100 %
b1110101 #
1"
#23400
0"
#23500
b1110101 %
b1110110 #
1"
#23600
0"
#23700
b1110110 %
b1110111 #
1"
#23800
0"
#23900
b1110111 %
b1111000 #
1"
#24000
0"
#24100
b1111000 %
b1111001 #
1"
#24200
0"
#24300
b1111001 %
b1111010 #
1"
#24400
0"
#24500
b1111010 %
b1111011 #
1"
#24600
0"
#24700
b1111011 %
b1111100 #
1"
#24800
0"
#24900
b1111100 %
b1111101 #
1"
#25000
0"
#25100
b1111101 %
b1111110 #
1"
#25200
0"
#25300
b1111110 %
b1111111 #
1"
#25400
0"
#25500
b1111111 %
b10000000 #
1"
#25600
0"
#25700
b10000000 %
b10000001 #
1"
#25800
0"
#25900
b10 &
1!
0$
b10000010 #
1"
#26000
0"
#26100
b11 &
0!
b10000011 #
1"
#26200
0"
#26300
b0 &
b10000100 #
1"
